MANIFEST.in
README.rst
setup.py
uetla/Database.py
uetla/MachineLearning.py
uetla/UETAnalytics.py
uetla/UETClassification.py
uetla/UETClustering.py
uetla/UETRegressor.py
uetla/__init__.py
uetla/createmodel.py
uetla/main.py
uetla/test.py
uetla.egg-info/PKG-INFO
uetla.egg-info/SOURCES.txt
uetla.egg-info/dependency_links.txt
uetla.egg-info/not-zip-safe
uetla.egg-info/requires.txt
uetla.egg-info/top_level.txt