Metadata-Version: 1.0
Name: uetla
Version: 0.2
Summary: UET Analytic for Moodle
Home-page: https://github.com/NguyenBach/UETBackend.git
Author: Bach Nguyen
Author-email: bachnq214@gmail.com
License: UNKNOWN
Keywords: Learning analytics
Platform: UNKNOWN
